midas/__init__.py
midas/driver.py
midas/faults.csv
midas/mock.py
midas/py.typed
midas/util.py
midas-0.8.0.dist-info/licenses/LICENSE
midas-0.8.0.dist-info/METADATA
midas-0.8.0.dist-info/WHEEL
midas-0.8.0.dist-info/entry_points.txt
midas-0.8.0.dist-info/top_level.txt
midas-0.8.0.dist-info/RECORD
