Metadata-Version: 2.4
Name: midas
Version: 0.8.0
Summary: Python driver for Honeywell Midas gas detectors.
Author-email: Pat Fuller <patrickfuller@gmail.com>
Maintainer-email: Alex Ruddick <alex@ruddick.tech>
Project-URL: Homepage, https://github.com/alexrudd2/midas
Project-URL: Issues, https://github.com/alexrudd2/midas/issues
Classifier: License :: OSI Approved :: GNU General Public License v2 (GPLv2)
Classifier: Development Status :: 4 - Beta
Classifier: Natural Language :: English
Classifier: Programming Language :: Python
Classifier: Programming Language :: Python :: 3
Classifier: Programming Language :: Python :: 3.10
Classifier: Programming Language :: Python :: 3.11
Classifier: Programming Language :: Python :: 3.12
Classifier: Programming Language :: Python :: 3.13
Classifier: Programming Language :: Python :: 3.14
Classifier: Topic :: Scientific/Engineering :: Human Machine Interfaces
Classifier: Topic :: Scientific/Engineering :: Electronic Design Automation (EDA)
License-File: LICENSE
Requires-Dist: pymodbus!=3.10.0,<3.12.0,>=3.0.2
Dynamic: license-file
